elsheeto/__init__.py
elsheeto/exceptions.py
elsheeto/facade.py
elsheeto/py.typed
elsheeto/version.py
elsheeto/models/__init__.py
elsheeto/models/aviti.py
elsheeto/models/common.py
elsheeto/models/csv_stage1.py
elsheeto/models/csv_stage2.py
elsheeto/models/illumina_v1.py
elsheeto/models/utils.py
elsheeto/parser/__init__.py
elsheeto/parser/aviti.py
elsheeto/parser/common.py
elsheeto/parser/illumina_v1.py
elsheeto/parser/stage1.py
elsheeto/parser/stage2.py
elsheeto/writer/__init__.py
elsheeto/writer/aviti.py
elsheeto/writer/base.py
elsheeto/writer/illumina_v1.py
elsheeto-0.3.0.dist-info/METADATA
elsheeto-0.3.0.dist-info/WHEEL
elsheeto-0.3.0.dist-info/licenses/AUTHORS.rst
elsheeto-0.3.0.dist-info/licenses/LICENSE
elsheeto-0.3.0.dist-info/RECORD
