Metadata-Version: 2.4
Name: elsheeto
Version: 0.3.0
Summary: I/O and models in type-annotated Python for NGS sample sheets: Illumina and Aviti
Project-URL: Documentation, https://github.com/medgen-mainz/elsheeto
Project-URL: Issues, https://github.com/medgen-mainz/elsheeto/issues
Project-URL: Source, https://github.com/medgen-mainz/elsheeto
Author: Manuel Holtgrewe
License-File: AUTHORS.rst
License-File: LICENSE
Classifier: Development Status :: 4 - Beta
Classifier: Intended Audience :: Developers
Classifier: License :: OSI Approved :: MIT License
Classifier: Natural Language :: English
Classifier: Programming Language :: Python :: 3
Classifier: Programming Language :: Python :: 3.13
Classifier: Programming Language :: Python :: 3.14
Classifier: Typing :: Typed
Requires-Python: >=3.13
Requires-Dist: pydantic<3.0,>=2.12
Requires-Dist: ruff>=0.14.2
